nextmeeting/__init__.py
nextmeeting/caldav.py
nextmeeting/cli.py
nextmeeting-3.0.0.dist-info/METADATA
nextmeeting-3.0.0.dist-info/WHEEL
nextmeeting-3.0.0.dist-info/entry_points.txt
nextmeeting-3.0.0.dist-info/licenses/LICENSE
nextmeeting-3.0.0.dist-info/RECORD
