Metadata-Version: 2.4
Name: nextmeeting
Version: 3.0.0
Summary: Show your nextmeeting in your poly/waybar with gcalcli
Author-email: Chmouel Boudjnah <chmouel@chmouel.com>
License-Expression: Apache-2.0
License-File: LICENSE
Keywords: calendar,cli
Classifier: License :: OSI Approved :: Apache Software License
Requires-Python: >=3.9
Requires-Dist: caldav>=1.3.9
Requires-Dist: python-dateutil>=2.9.0.post0
